falcon_mongo_middleware/__init__.py
falcon_mongo_middleware/mongo_middleware.py
falcon_mongo_middleware-0.1.16.dist-info/LICENSE
falcon_mongo_middleware-0.1.16.dist-info/WHEEL
falcon_mongo_middleware-0.1.16.dist-info/METADATA
falcon_mongo_middleware-0.1.16.dist-info/RECORD
